omikuji/_libomikuji__lib.so
omikuji/__init__.py
omikuji/_libomikuji__ffi.py
omikuji/_libomikuji.py
omikuji-0.5.1.dist-info/LICENSE
omikuji-0.5.1.dist-info/WHEEL
omikuji-0.5.1.dist-info/METADATA
omikuji-0.5.1.dist-info/RECORD
omikuji-0.5.1.dist-info/top_level.txt
